pandas_genomics/__init__.py
pandas_genomics/accessors/__init__.py
pandas_genomics/accessors/dataframe_accessor.py
pandas_genomics/accessors/series_accessor.py
pandas_genomics/accessors/utils/__init__.py
pandas_genomics/accessors/utils/edge_encoding.py
pandas_genomics/arrays/__init__.py
pandas_genomics/arrays/encoding_mixin.py
pandas_genomics/arrays/genotype_array.py
pandas_genomics/arrays/info_mixin.py
pandas_genomics/arrays/utils.py
pandas_genomics/io/__init__.py
pandas_genomics/io/bed.py
pandas_genomics/io/plink/__init__.py
pandas_genomics/io/plink/from_plink.py
pandas_genomics/io/plink/to_plink.py
pandas_genomics/io/vcf.py
pandas_genomics/scalars.py
pandas_genomics/sim/__init__.py
pandas_genomics/sim/biallelic_model_simulator.py
pandas_genomics/sim/random_gt.py
pandas_genomics-1.0.1.dist-info/LICENSE
pandas_genomics-1.0.1.dist-info/METADATA
pandas_genomics-1.0.1.dist-info/WHEEL
pandas_genomics-1.0.1.dist-info/RECORD
