Metadata-Version: 2.1
Name: pandas-genomics
Version: 1.0.1
Summary: Pandas ExtensionDtypes and ExtensionArray for working with genomics data
Home-page: https://github.com/HallLab/pandas-genomics/
License: BSD-3-Clause
Author: Andre Rico
Author-email: alr6366@psu.edu
Requires-Python: >=3.10,<3.13
Classifier: Development Status :: 3 - Alpha
Classifier: Intended Audience :: Science/Research
Classifier: License :: OSI Approved :: BSD License
Classifier: Programming Language :: Python :: 3
Classifier: Programming Language :: Python :: 3.10
Classifier: Programming Language :: Python :: 3.11
Classifier: Programming Language :: Python :: 3.12
Classifier: Topic :: Scientific/Engineering :: Bio-Informatics
Provides-Extra: docs
Requires-Dist: cyvcf2 (>=0.31.1) ; sys_platform != "win32"
Requires-Dist: importlib-metadata (>=2.0,<3.0) ; python_version < "3.8"
Requires-Dist: ipython (>=7.18.1,<8.0.0) ; extra == "docs"
Requires-Dist: numpy (>=1.24,<2.0)
Requires-Dist: numpydoc (>=1.1.0,<2.0.0) ; extra == "docs"
Requires-Dist: pandas (>=2.2,<3.0)
Requires-Dist: scipy (>=1.9,<2.0)
Requires-Dist: sphinx (>=4.0.0,<5.0.0) ; extra == "docs"
Requires-Dist: sphinx-copybutton (>=0.3.0,<0.4.0) ; extra == "docs"
Requires-Dist: sphinx_rtd_theme (>=0.5.0,<0.6.0) ; extra == "docs"
Requires-Dist: statsmodels (>=0.14,<0.15)
Project-URL: Documentation, https://pandas-genomics.readthedocs.io/en/latest/
Project-URL: Repository, https://github.com/HallLab/pandas-genomics/
